README
flask_mako.py
setup.py
test_flask_mako.py
Flask_Mako.egg-info/PKG-INFO
Flask_Mako.egg-info/SOURCES.txt
Flask_Mako.egg-info/dependency_links.txt
Flask_Mako.egg-info/not-zip-safe
Flask_Mako.egg-info/requires.txt
Flask_Mako.egg-info/top_level.txt