Metadata-Version: 1.1
Name: Flask-Mako
Version: 0.1
Summary: Adds Mako templating support to Flask
Home-page: https://github.com/AnIrishDuck/flask-mako
Author: Frank Murphy
Author-email: fpmurphy@mtu.edu
License: MIT
Platform: any
Classifier: Environment :: Web Environment
Classifier: Intended Audience :: Developers
Classifier: License :: OSI Approved :: BSD License
Classifier: Operating System :: OS Independent
Classifier: Programming Language :: Python
Classifier: Topic :: Internet :: WWW/HTTP :: Dynamic Content
Classifier: Topic :: Software Development :: Libraries :: Python Modules
